{
  "resource": {
    "github_repository": {
      "cbp_bus_sign": {
        "description": "READ-ONLY MIRROR",
        "has_discussions": false,
        "has_issues": false,
        "has_projects": false,
        "has_wiki": false,
        "homepage_url": "https://codeberg.org/ScottyLabs/bus-sign",
        "name": "bus-sign",
        "visibility": "public"
      },
      "devops_devenv": {
        "description": "READ-ONLY MIRROR",
        "has_discussions": false,
        "has_issues": false,
        "has_projects": false,
        "has_wiki": false,
        "homepage_url": "https://codeberg.org/ScottyLabs/devenv",
        "name": "devenv",
        "visibility": "public"
      },
      "devops_governance": {
        "description": "READ-ONLY MIRROR",
        "has_discussions": false,
        "has_issues": false,
        "has_projects": false,
        "has_wiki": false,
        "homepage_url": "https://codeberg.org/ScottyLabs/governance",
        "name": "governance",
        "visibility": "public"
      },
      "devops_infrastructure": {
        "description": "READ-ONLY MIRROR",
        "has_discussions": false,
        "has_issues": false,
        "has_projects": false,
        "has_wiki": false,
        "homepage_url": "https://codeberg.org/ScottyLabs/infrastructure",
        "name": "infrastructure",
        "visibility": "public"
      },
      "devops_kennel": {
        "description": "READ-ONLY MIRROR",
        "has_discussions": false,
        "has_issues": false,
        "has_projects": false,
        "has_wiki": false,
        "homepage_url": "https://codeberg.org/ScottyLabs/kennel",
        "name": "kennel",
        "visibility": "public"
      }
    },
    "github_repository_deploy_key": {
      "cbp_bus_sign_mirror_deploy_key": {
        "key": "${restapi_object.cbp_bus_sign_push_mirror.api_data.public_key}",
        "read_only": false,
        "repository": "${github_repository.cbp_bus_sign.name}",
        "title": "Codeberg Mirroring"
      },
      "devops_devenv_mirror_deploy_key": {
        "key": "${restapi_object.devops_devenv_push_mirror.api_data.public_key}",
        "read_only": false,
        "repository": "${github_repository.devops_devenv.name}",
        "title": "Codeberg Mirroring"
      },
      "devops_governance_mirror_deploy_key": {
        "key": "${restapi_object.devops_governance_push_mirror.api_data.public_key}",
        "read_only": false,
        "repository": "${github_repository.devops_governance.name}",
        "title": "Codeberg Mirroring"
      },
      "devops_infrastructure_mirror_deploy_key": {
        "key": "${restapi_object.devops_infrastructure_push_mirror.api_data.public_key}",
        "read_only": false,
        "repository": "${github_repository.devops_infrastructure.name}",
        "title": "Codeberg Mirroring"
      },
      "devops_kennel_mirror_deploy_key": {
        "key": "${restapi_object.devops_kennel_push_mirror.api_data.public_key}",
        "read_only": false,
        "repository": "${github_repository.devops_kennel.name}",
        "title": "Codeberg Mirroring"
      }
    },
    "github_repository_ruleset": {
      "cbp_bus_sign_ruleset": {
        "bypass_actors": [
          {
            "actor_id": "${tonumber(element(split(\":\", github_repository_deploy_key.cbp_bus_sign_mirror_deploy_key.id), 1))}",
            "actor_type": "DeployKey",
            "bypass_mode": "always"
          }
        ],
        "conditions": {
          "ref_name": {
            "exclude": [],
            "include": [
              "~ALL"
            ]
          }
        },
        "enforcement": "active",
        "name": "Default",
        "repository": "${github_repository.cbp_bus_sign.name}",
        "rules": {
          "creation": true,
          "deletion": true,
          "non_fast_forward": true,
          "pull_request": {
            "required_approving_review_count": 1
          },
          "update": true
        },
        "target": "branch"
      },
      "devops_devenv_ruleset": {
        "bypass_actors": [
          {
            "actor_id": "${tonumber(element(split(\":\", github_repository_deploy_key.devops_devenv_mirror_deploy_key.id), 1))}",
            "actor_type": "DeployKey",
            "bypass_mode": "always"
          }
        ],
        "conditions": {
          "ref_name": {
            "exclude": [],
            "include": [
              "~ALL"
            ]
          }
        },
        "enforcement": "active",
        "name": "Default",
        "repository": "${github_repository.devops_devenv.name}",
        "rules": {
          "creation": true,
          "deletion": true,
          "non_fast_forward": true,
          "pull_request": {
            "required_approving_review_count": 1
          },
          "update": true
        },
        "target": "branch"
      },
      "devops_governance_ruleset": {
        "bypass_actors": [
          {
            "actor_id": "${tonumber(element(split(\":\", github_repository_deploy_key.devops_governance_mirror_deploy_key.id), 1))}",
            "actor_type": "DeployKey",
            "bypass_mode": "always"
          }
        ],
        "conditions": {
          "ref_name": {
            "exclude": [],
            "include": [
              "~ALL"
            ]
          }
        },
        "enforcement": "active",
        "name": "Default",
        "repository": "${github_repository.devops_governance.name}",
        "rules": {
          "creation": true,
          "deletion": true,
          "non_fast_forward": true,
          "pull_request": {
            "required_approving_review_count": 1
          },
          "update": true
        },
        "target": "branch"
      },
      "devops_infrastructure_ruleset": {
        "bypass_actors": [
          {
            "actor_id": "${tonumber(element(split(\":\", github_repository_deploy_key.devops_infrastructure_mirror_deploy_key.id), 1))}",
            "actor_type": "DeployKey",
            "bypass_mode": "always"
          }
        ],
        "conditions": {
          "ref_name": {
            "exclude": [],
            "include": [
              "~ALL"
            ]
          }
        },
        "enforcement": "active",
        "name": "Default",
        "repository": "${github_repository.devops_infrastructure.name}",
        "rules": {
          "creation": true,
          "deletion": true,
          "non_fast_forward": true,
          "pull_request": {
            "required_approving_review_count": 1
          },
          "update": true
        },
        "target": "branch"
      },
      "devops_kennel_ruleset": {
        "bypass_actors": [
          {
            "actor_id": "${tonumber(element(split(\":\", github_repository_deploy_key.devops_kennel_mirror_deploy_key.id), 1))}",
            "actor_type": "DeployKey",
            "bypass_mode": "always"
          }
        ],
        "conditions": {
          "ref_name": {
            "exclude": [],
            "include": [
              "~ALL"
            ]
          }
        },
        "enforcement": "active",
        "name": "Default",
        "repository": "${github_repository.devops_kennel.name}",
        "rules": {
          "creation": true,
          "deletion": true,
          "non_fast_forward": true,
          "pull_request": {
            "required_approving_review_count": 1
          },
          "update": true
        },
        "target": "branch"
      }
    }
  }
}